spacy_chapas/__init__.py
spacy_chapas/chapas.py
spacy_chapas/chapas2ud
spacy_chapas/unidic2ipadic
spacy_chapas-0.9.3.data/data/bin/chapas2ud
spacy_chapas-0.9.3.dist-info/LICENSE.txt
spacy_chapas-0.9.3.dist-info/METADATA
spacy_chapas-0.9.3.dist-info/WHEEL
spacy_chapas-0.9.3.dist-info/top_level.txt
spacy_chapas-0.9.3.dist-info/RECORD
