Metadata-Version: 2.1
Name: spacy-chapas
Version: 0.9.3
Summary: ChaPAS-CaboCha-MeCab wrapper for spaCy
Home-page: https://github.com/KoichiYasuoka/spaCy-ChaPAS
Author: Koichi Yasuoka
Author-email: yasuoka@kanji.zinbun.kyoto-u.ac.jp
License: MIT
Project-URL: ChaPAS, https://sites.google.com/site/yotarow/chapas
Project-URL: CaboCha, https://taku910.github.io/cabocha/
Project-URL: MeCab, https://taku910.github.io/mecab/
Project-URL: Source, https://github.com/KoichiYasuoka/spaCy-ChaPAS
Project-URL: Tracker, https://github.com/KoichiYasuoka/spaCy-ChaPAS/issues
Keywords: spacy nlp
Classifier: License :: OSI Approved :: MIT License
Classifier: Programming Language :: Python :: 3
Classifier: Operating System :: OS Independent
Classifier: Topic :: Text Processing :: Linguistic
Classifier: Natural Language :: Japanese
Requires-Python: >=3.6
License-File: LICENSE.txt
Requires-Dist: deplacy (>=2.1.0)
Requires-Dist: spacy (>=2.2.2)
